omniface/__init__.py
omniface/main.so
omniface/app/__init__.py
omniface/app/common.so
omniface/app/face_analysis.so
omniface/model_zoo/__init__.py
omniface/model_zoo/arcface.so
omniface/model_zoo/model_zoo.so
omniface/model_zoo/retinaface.so
omniface/utils/__init__.py
omniface/utils/face_align.so
omniface-1.0.0.dist-info/METADATA
omniface-1.0.0.dist-info/WHEEL
omniface-1.0.0.dist-info/top_level.txt
omniface-1.0.0.dist-info/RECORD
